CHANGES.txt
LICENSE.txt
MANIFEST.in
README.md
README.txt
bootstrap
setup.py
db2rest/__init__.py
db2rest/app.py
db2rest/auth.py
db2rest/config.example
db2rest/db.py
db2rest/exceptions.py
db2rest/helpers.py
db2rest/renderer.py
db2rest/rest.py
db2rest/version.py
db2rest.egg-info/PKG-INFO
db2rest.egg-info/SOURCES.txt
db2rest.egg-info/dependency_links.txt
db2rest.egg-info/entry_points.txt
db2rest.egg-info/requires.txt
db2rest.egg-info/top_level.txt
db2rest/static/style.css
db2rest/templates/Table.html
db2rest/templates/Tables.html
db2rest/templates/layout.html
db2rest/test/__init__.py
doc/Makefile
doc/build/doctrees/environment.pickle
doc/build/doctrees/index.doctree
doc/build/html/.buildinfo
doc/build/html/genindex.html
doc/build/html/index.html
doc/build/html/objects.inv
doc/build/html/py-modindex.html
doc/build/html/search.html
doc/build/html/searchindex.js
doc/build/html/_modules/index.html
doc/build/html/_modules/io.html
doc/build/html/_modules/db2rest/app.html
doc/build/html/_modules/db2rest/db.html
doc/build/html/_modules/db2rest/exceptions.html
doc/build/html/_modules/db2rest/helpers.html
doc/build/html/_modules/db2rest/rest.html
doc/build/html/_sources/index.txt
doc/build/html/_static/ajax-loader.gif
doc/build/html/_static/basic.css
doc/build/html/_static/comment-bright.png
doc/build/html/_static/comment-close.png
doc/build/html/_static/comment.png
doc/build/html/_static/default.css
doc/build/html/_static/doctools.js
doc/build/html/_static/down-pressed.png
doc/build/html/_static/down.png
doc/build/html/_static/file.png
doc/build/html/_static/jquery.js
doc/build/html/_static/minus.png
doc/build/html/_static/plus.png
doc/build/html/_static/pygments.css
doc/build/html/_static/searchtools.js
doc/build/html/_static/sidebar.js
doc/build/html/_static/underscore.js
doc/build/html/_static/up-pressed.png
doc/build/html/_static/up.png
doc/build/html/_static/websupport.js
doc/source/conf.py
doc/source/index.rst
scripts/db2rest-tests.py