Metadata-Version: 1.1
Name: db2rest
Version: 0.1.6
Summary: A HTTP REST API for relational databases
Home-page: https://bitbucket.org/nikpalumbo/db2rest
Author: Nicola Palumbo
Author-email: nikpalumbo@gmail.com
License: UNKNOWN
Keywords: database,HTTP rest
Platform: UNKNOWN
Classifier: Development Status :: 3 - Alpha
Classifier: Environment :: Console
Classifier: Intended Audience :: Developers
Classifier: Intended Audience :: System Administrators
Classifier: License :: OSI Approved :: MIT License
Classifier: Operating System :: MacOS :: MacOS X
Classifier: Operating System :: Microsoft :: Windows
Classifier: Operating System :: POSIX
Classifier: Programming Language :: Python
Classifier: Topic :: Communications :: Email
